{
  "2026-02-10": {
    "date": "2026-02-10",
    "doing": [
      "[REF-002] API usage & cost tracking - Track tokens, cost estimates, spending thresholds per task"
    ],
    "completed": [
      "[REF-001] Documentation & User Guide - Created comprehensive docs for dashboard (USER_GUIDE.md, TECHNICAL.md)"
    ],
    "next": [
      "[REF-003] Review documentation - Verify docs are easy to read, logical, comprehensive",
      "[REF-004] Dashboard priority queue update - Add reference numbers, priority reordering, stop button for active tasks"
    ],
    "notes": ""
  }
}